kafkaposted/__init__.py
kafkaposted/base.py
kafkaposted/tests/__init__.py
kafkaposted/tests/test_base.py
kafkaposted-0.1.4.dist-info/LICENSE
kafkaposted-0.1.4.dist-info/METADATA
kafkaposted-0.1.4.dist-info/WHEEL
kafkaposted-0.1.4.dist-info/top_level.txt
kafkaposted-0.1.4.dist-info/RECORD
