Metadata-Version: 2.1
Name: kafkaposted
Version: 0.1.4
Summary: Concrete implementation of posted for Kafka
License: mit
License-File: LICENSE
Requires-Dist: kafka-python ==2.0.2
Requires-Dist: posted
